myfunctions_ilonaserg/__init__.py
myfunctions_ilonaserg/math.py
myfunction_ilonaserg-0.0.6.dist-info/METADATA
myfunction_ilonaserg-0.0.6.dist-info/WHEEL
myfunction_ilonaserg-0.0.6.dist-info/top_level.txt
myfunction_ilonaserg-0.0.6.dist-info/RECORD
