Metadata-Version: 2.1
Name: myfunction-ilonaserg
Version: 0.0.6
Summary: A description of your package
Home-page: https://github.com/ilonaserg/
Author: Ilona Sergeeva
Author-email: asteria2009scorp@gmail.com
License: MIT
Platform: UNKNOWN
Classifier: Programming Language :: Python :: 3
Classifier: License :: OSI Approved :: MIT License
Classifier: Operating System :: OS Independent
Requires-Python: >=3.6
Requires-Dist: os
